calcE_test/__init__.py
calcE_test/calcE.py
calcE_test-0.1.0.dist-info/METADATA
calcE_test-0.1.0.dist-info/WHEEL
calcE_test-0.1.0.dist-info/top_level.txt
calcE_test-0.1.0.dist-info/RECORD
